{"notes":"Woodpath4-S *:10238","onload":{"preload":{"audio":["ARLiteWindMov"],"images":["161\/bg.jpg","161\/WoodPath4-S (Switch-on).jpeg"]}},"onrendercomplete":{},"navigation":[{"width":"367","height":"143","left":"172","bottom":"0","goto":"@159","cursor":"up"},{"width":"41","height":"333","bottom":"0","right":"0","goto":"@73","cursor":"right"},{"width":"233","height":"280","left":"0","bottom":"050","goto":"@71","cursor":"up"},{"width":"87","height":"159","left":"0","bottom":"0","goto":"@73","cursor":"left"},{"width":"220","height":"153","left":"293","bottom":"133","goto":"@159","cursor":"up"}],"ambience":{"source":"ARLiteWindMov","volume":0.9},"background":"161\/bg.jpg","content":[{"tag":"div","attr":{},"css":{"bottom":"191px","left":"3px","width":"41px","height":"34px","background-image":"url('\/assets\/161\/WoodPath4-S (Switch-on).jpeg')","display":"none"},"events":{}}]}